pod_gpt/__init__.py
pod_gpt/indexer.py
pod_gpt/models/__init__.py
pod_gpt/models/models.py
pod_gpt/scraper.py
pod_gpt-0.0.7.dist-info/WHEEL
pod_gpt-0.0.7.dist-info/METADATA
pod_gpt-0.0.7.dist-info/RECORD
